sobolt
