Metadata-Version: 1.0
Name: sobolt
Version: 0.1.4
Summary: Client code to query Sobolt's AI services
Home-page: http://sobolt.com
Author: Sobolt
Author-email: info@sobolt.com
License: All rights reserved
Platform: UNKNOWN
